nisyscfg/VERSION
nisyscfg/__init__.py
nisyscfg/_lib.py
nisyscfg/_library.py
nisyscfg/_library_singleton.py
nisyscfg/component_info.py
nisyscfg/dependency_info.py
nisyscfg/enums.py
nisyscfg/errors.py
nisyscfg/expert_info.py
nisyscfg/filter.py
nisyscfg/hardware_resource.py
nisyscfg/properties.py
nisyscfg/software_feed.py
nisyscfg/system.py
nisyscfg/system_info.py
nisyscfg/timestamp.py
nisyscfg/types.py
nisyscfg/pxi/__init__.py
nisyscfg/pxi/enums.py
nisyscfg/pxi/properties.py
nisyscfg/xnet/__init__.py
nisyscfg/xnet/enums.py
nisyscfg/xnet/properties.py
tests/__init__.py
tests/test_import.py
tests/test_session.py
nisyscfg-0.2.1.dist-info/LICENSE
nisyscfg-0.2.1.dist-info/METADATA
nisyscfg-0.2.1.dist-info/WHEEL
nisyscfg-0.2.1.dist-info/top_level.txt
nisyscfg-0.2.1.dist-info/zip-safe
nisyscfg-0.2.1.dist-info/RECORD
