Metadata-Version: 2.1
Name: nisyscfg
Version: 0.2.1
Summary: NI System Configuration Python API
Home-page: https://github.com/tkrebes/nisyscfg-python
Author: National Instruments
Maintainer: Tyler Krehbiel
Maintainer-email: tyler.krehbiel@emerson.com
License: MIT
Keywords: nisyscfg,syscfg
Platform: UNKNOWN
Classifier: Development Status :: 1 - Planning
Classifier: Intended Audience :: Developers
Classifier: Intended Audience :: Manufacturing
Classifier: Intended Audience :: Science/Research
Classifier: License :: OSI Approved :: MIT License
Classifier: Operating System :: Microsoft :: Windows
Classifier: Operating System :: POSIX
Classifier: Programming Language :: Python :: 3
Classifier: Programming Language :: Python :: 3.9
Classifier: Programming Language :: Python :: 3.10
Classifier: Programming Language :: Python :: 3.11
Classifier: Programming Language :: Python :: 3.12
Classifier: Programming Language :: Python :: 3.13
Classifier: Topic :: System :: Hardware :: Hardware Drivers
Requires-Python: >=3.9
License-File: LICENSE
Requires-Dist: hightime
Requires-Dist: six
